keypoint_moseq
